{
  "light": [{
      "x": 8496,
      "y": 300
    },
    {
      "x": 8497,
      "y": 335
    },
    {
      "x": 8498,
      "y": 355
    },
    {
      "x": 8499,
      "y": 332
    },
    {
      "x": 8500,
      "y": 378
    },
    {
      "x": 8501,
      "y": 394
    },
    {
      "x": 8502,
      "y": 362
    },
    {
      "x": 8503,
      "y": 396
    },
    {
      "x": 8504,
      "y": 475
    },
    {
      "x": 8505,
      "y": 502
    },
    {
      "x": 8506,
      "y": 411
    },
    {
      "x": 8507,
      "y": 379
    },
    {
      "x": 8508,
      "y": 376
    },
    {
      "x": 8509,
      "y": 433
    },
    {
      "x": 8510,
      "y": 487
    },
    {
      "x": 8511,
      "y": 525
    },
    {
      "x": 8512,
      "y": 545
    },
    {
      "x": 8513,
      "y": 502
    },
    {
      "x": 8514,
      "y": 456
    },
    {
      "x": 8515,
      "y": 541
    },
    {
      "x": 8516,
      "y": 558
    },
    {
      "x": 8517,
      "y": 552
    },
    {
      "x": 8518,
      "y": 524
    },
    {
      "x": 8519,
      "y": 501
    },
    {
      "x": 8520,
      "y": 456
    },
    {
      "x": 8521,
      "y": 455
    },
    {
      "x": 8522,
      "y": 455
    },
    {
      "x": 8523,
      "y": 447
    },
    {
      "x": 8524,
      "y": 419
    },
    {
      "x": 8525,
      "y": 419
    },
    {
      "x": 8526,
      "y": 424
    },
    {
      "x": 8527,
      "y": 425
    },
    {
      "x": 8528,
      "y": 425
    },
    {
      "x": 8529,
      "y": 425
    },
    {
      "x": 8530,
      "y": 425
    },
    {
      "x": 8531,
      "y": 428
    },
    {
      "x": 8532,
      "y": 431
    },
    {
      "x": 8533,
      "y": 432
    },
    {
      "x": 8534,
      "y": 435
    },
    {
      "x": 8535,
      "y": 748
    },
    {
      "x": 8536,
      "y": 826
    },
    {
      "x": 8537,
      "y": 839
    },
    {
      "x": 8538,
      "y": 844
    },
    {
      "x": 8539,
      "y": 848
    },
    {
      "x": 8540,
      "y": 850
    },
    {
      "x": 8541,
      "y": 851
    },
    {
      "x": 8542,
      "y": 851
    },
    {
      "x": 8543,
      "y": 849
    },
    {
      "x": 8544,
      "y": 847
    },
    {
      "x": 8545,
      "y": 844
    }
  ]
}